mkcpr/Config.py
mkcpr/Error.py
mkcpr/Util.py
mkcpr/__init__.py
mkcpr/main.py
mkcpr-1.2.1.dist-info/entry_points.txt
mkcpr-1.2.1.dist-info/LICENSE
mkcpr-1.2.1.dist-info/WHEEL
mkcpr-1.2.1.dist-info/METADATA
mkcpr-1.2.1.dist-info/RECORD
