Metadata-Version: 2.1
Name: mkcpr
Version: 1.2.1
Summary: mkcpr is a command line utility that helps you to build your Competitive Programming Reference in PDF.
Home-page: https://github.com/searleser97/mkcpr
License: AGPL-3.0-only
Keywords: competitive,programming,reference,tool
Author: searleser97
Author-email: serchgabriel97@gmail.com
Requires-Python: >=3.5,<4.0
Classifier: License :: OSI Approved :: GNU Affero General Public License v3
Classifier: Programming Language :: Python :: 3
Classifier: Programming Language :: Python :: 3.5
Classifier: Programming Language :: Python :: 3.6
Classifier: Programming Language :: Python :: 3.7
Classifier: Programming Language :: Python :: 3.8
Project-URL: Repository, https://github.com/searleser97/mkcpr
